jupyterlab_marimo/__init__.py
jupyterlab_marimo/_version.py
jupyterlab_marimo/icon.svg
jupyterlab_marimo/jupyter_marimo_proxy.py
jupyterlab_marimo/labextension/package.json
jupyterlab_marimo/labextension/static/132.21ac2dede6c0eaf82fb9.js
jupyterlab_marimo/labextension/static/181.1f0480ff8724a92ae8f6.js
jupyterlab_marimo/labextension/static/remoteEntry.75c8d1686fed038a8b9a.js
jupyterlab_marimo/labextension/static/style.js
jupyterlab_marimo/labextension/static/third-party-licenses.json
jupyterlab_marimo-0.1.1.data/data/share/jupyter/labextensions/jupyterlab-marimo/package.json
jupyterlab_marimo-0.1.1.data/data/share/jupyter/labextensions/jupyterlab-marimo/static/132.21ac2dede6c0eaf82fb9.js
jupyterlab_marimo-0.1.1.data/data/share/jupyter/labextensions/jupyterlab-marimo/static/181.1f0480ff8724a92ae8f6.js
jupyterlab_marimo-0.1.1.data/data/share/jupyter/labextensions/jupyterlab-marimo/static/remoteEntry.75c8d1686fed038a8b9a.js
jupyterlab_marimo-0.1.1.data/data/share/jupyter/labextensions/jupyterlab-marimo/static/style.js
jupyterlab_marimo-0.1.1.data/data/share/jupyter/labextensions/jupyterlab-marimo/static/third-party-licenses.json
jupyterlab_marimo-0.1.1.dist-info/METADATA
jupyterlab_marimo-0.1.1.dist-info/WHEEL
jupyterlab_marimo-0.1.1.dist-info/entry_points.txt
jupyterlab_marimo-0.1.1.dist-info/licenses/LICENSE
jupyterlab_marimo-0.1.1.dist-info/RECORD
