Metadata-Version: 2.4
Name: jupyterlab-marimo
Version: 0.1.1
Dynamic: Keywords
Summary: A JupyterLab extension to open Marimo files in an embbeded Marimo editor
Project-URL: Homepage, https://github.com/mthiboust/jupyterlab-marimo
Project-URL: Bug Tracker, https://github.com/mthiboust/jupyterlab-marimo/issues
Project-URL: Repository, https://github.com/mthiboust/jupyterlab-marimo
Author: Matthieu Thiboust
License:                                  Apache License
License-File: LICENSE
Classifier: Framework :: Jupyter
Classifier: Framework :: Jupyter :: JupyterLab
Classifier: Framework :: Jupyter :: JupyterLab :: 4
Classifier: Framework :: Jupyter :: JupyterLab :: Extensions
Classifier: Framework :: Jupyter :: JupyterLab :: Extensions :: Prebuilt
Classifier: License :: OSI Approved :: BSD License
Classifier: Programming Language :: Python
Classifier: Programming Language :: Python :: 3
Classifier: Programming Language :: Python :: 3.8
Classifier: Programming Language :: Python :: 3.9
Classifier: Programming Language :: Python :: 3.10
Classifier: Programming Language :: Python :: 3.11
Classifier: Programming Language :: Python :: 3.12
Requires-Python: >=3.8
Requires-Dist: jupyter-server-proxy
Requires-Dist: marimo>=0.6.21
Requires-Dist: matplotlib>=3.7.5
Requires-Dist: numpy>=1.24.4
Provides-Extra: dev
Requires-Dist: jupyterlab<5,>=4.0.0; extra == 'dev'
